imdb_sqlite/__init__.py
imdb_sqlite/__main__.py
imdb_sqlite-1.1.0.dist-info/LICENSE
imdb_sqlite-1.1.0.dist-info/METADATA
imdb_sqlite-1.1.0.dist-info/WHEEL
imdb_sqlite-1.1.0.dist-info/entry_points.txt
imdb_sqlite-1.1.0.dist-info/top_level.txt
imdb_sqlite-1.1.0.dist-info/RECORD
