Metadata-Version: 2.1
Name: imdb-sqlite
Version: 1.1.0
Summary: Imports IMDB TSV files into a SQLite database
Home-page: https://github.com/jojje/imdb-sqlite
Author: Jonas Tingeborn
Author-email: tinjon+pip@gmail.com
License: GNU GPL v2
Classifier: Programming Language :: Python :: 2.7
Classifier: Programming Language :: Python :: 3
Classifier: License :: OSI Approved :: GNU General Public License v2 (GPLv2)
Classifier: Operating System :: OS Independent
License-File: LICENSE
Requires-Dist: tqdm (>=4.4.1)
